{
  "topic": {
    "item": "dyslip",
    "subject": "cardio"
  },
  "metadata": {
    "batch": "IA_aout"
  },
  "question": [
    {
      "published": false,
      "id": "AIgenerated_1756050582216_01",
      "current_version_epoch_ms": 1756050582216,
      "rang": "A",
      "topic": {
        "subject": "cardio",
        "item": "dyslip"
      },
      "data": {
        "statement": "Parmi les trois grands types de dyslipidémies, lequel est caractérisé par une augmentation isolée du cholestérol plasmatique ?",
        "propositions": [
          {
            "correct": true,
            "proposition": "Hypercholestérolémie pure",
            "justification": "L'hypercholestérolémie pure est définie par une élévation isolée du cholestérol plasmatique, sans augmentation des triglycérides."
          },
          {
            "correct": false,
            "proposition": "Hypertriglycéridémie pure",
            "justification": "L'hypertriglycéridémie pure se caractérise par une augmentation isolée des triglycérides, pas du cholestérol."
          },
          {
            "correct": false,
            "proposition": "Hyperlipidémie mixte",
            "justification": "L'hyperlipidémie mixte implique à la fois une élévation du cholestérol et des triglycérides, contrairement à l'hypercholestérolémie pure."
          },
          {
            "correct": false,
            "proposition": "Hyperlipidémie secondaire",
            "justification": "Les hyperlipidémies secondaires sont liées à des causes externes, comme des maladies ou des médicaments, et ne sont pas un type de dyslipidémie primaire."
          },
          {
            "correct": false,
            "proposition": "Dyslipidémie associée au diabète de type 2",
            "justification": "La dyslipidémie associée au diabète de type 2 inclut à la fois une élévation des triglycérides et une diminution du cholestérol HDL, ce qui diffère des hypercholestérolémies pures."
          }
        ]
      }
    },
    {
      "published": false,
      "id": "AIgenerated_1756050582216_02",
      "current_version_epoch_ms": 1756050582216,
      "rang": "A",
      "topic": {
        "subject": "cardio",
        "item": "dyslip"
      },
      "data": {
        "statement": "Quelle dyslipidémie est souvent associée au diabète de type 2 et au syndrome métabolique ?",
        "propositions": [
          {
            "correct": true,
            "proposition": "Dyslipidémie associée au diabète de type 2",
            "justification": "Cette dyslipidémie est caractérisée par des niveaux élevés de triglycérides et une diminution du cholestérol HDL, fréquemment observée dans le diabète de type 2 et le syndrome métabolique."
          },
          {
            "correct": false,
            "proposition": "Hypercholestérolémie pure",
            "justification": "L'hypercholestérolémie pure concerne principalement une élévation du cholestérol, sans association avec le diabète de type 2 ou le syndrome métabolique."
          },
          {
            "correct": false,
            "proposition": "Hypertriglycéridémie pure",
            "justification": "L'hypertriglycéridémie pure correspond uniquement à une élévation des triglycérides et n'est pas spécifiquement liée au diabète de type 2 ou au syndrome métabolique."
          },
          {
            "correct": false,
            "proposition": "Hyperlipidémie secondaire",
            "justification": "Les hyperlipidémies secondaires sont dues à des causes externes, telles que des médicaments ou d'autres pathologies, et ne sont pas une dyslipidémie associée spécifiquement au diabète de type 2."
          },
          {
            "correct": false,
            "proposition": "Hyperlipidémie mixte",
            "justification": "Bien que l'hyperlipidémie mixte implique à la fois des élévations du cholestérol et des triglycérides, elle n'est pas directement associée au diabète de type 2."
          }
        ]
      }
    },
    {
      "published": false,
      "id": "AIgenerated_1756050582216_03",
      "current_version_epoch_ms": 1756050582216,
      "rang": "A",
      "topic": {
        "subject": "cardio",
        "item": "dyslip"
      },
      "data": {
        "statement": "Quelles sont les causes principales des hyperlipidémies secondaires ?",
        "propositions": [
          {
            "correct": true,
            "proposition": "Maladies ou médicaments",
            "justification": "Les hyperlipidémies secondaires sont principalement causées par des maladies sous-jacentes ou l'usage de médicaments, comme les diurétiques ou les corticoïdes."
          },
          {
            "correct": false,
            "proposition": "Diabète de type 2",
            "justification": "Le diabète de type 2 est associé à une dyslipidémie spécifique, mais n'est pas une cause d'hyperlipidémie secondaire."
          },
          {
            "correct": false,
            "proposition": "Hypercholestérolémie pure",
            "justification": "L'hypercholestérolémie pure est une forme primaire de dyslipidémie et non une forme secondaire causée par une autre pathologie."
          },
          {
            "correct": false,
            "proposition": "Hypertriglycéridémie pure",
            "justification": "L'hypertriglycéridémie pure est également une forme primaire et non secondaire de dyslipidémie."
          },
          {
            "correct": false,
            "proposition": "Dyslipidémie mixte",
            "justification": "Les dyslipidémies mixtes impliquent une élévation du cholestérol et des triglycérides, mais elles ne sont pas spécifiquement liées à des causes secondaires comme les médicaments ou les maladies."
          }
        ]
      }
    },
    {
      "published": false,
      "id": "AIgenerated_1756050582216_04",
      "current_version_epoch_ms": 1756050582216,
      "rang": "A",
      "topic": {
        "subject": "cardio",
        "item": "dyslip"
      },
      "data": {
        "statement": "Parmi les types de dyslipidémies, lequel est caractérisé par une élévation simultanée des cholestérols et des triglycérides ?",
        "propositions": [
          {
            "correct": true,
            "proposition": "Hyperlipidémie mixte",
            "justification": "L'hyperlipidémie mixte est définie par une augmentation simultanée des cholestérols et des triglycérides, ce qui la distingue des autres formes de dyslipidémies."
          },
          {
            "correct": false,
            "proposition": "Hypercholestérolémie pure",
            "justification": "L'hypercholestérolémie pure se caractérise par une élévation isolée du cholestérol, sans augmentation des triglycérides."
          },
          {
            "correct": false,
            "proposition": "Hypertriglycéridémie pure",
            "justification": "L'hypertriglycéridémie pure est spécifiquement une élévation des triglycérides, sans élévation du cholestérol."
          },
          {
            "correct": false,
            "proposition": "Hyperlipidémie secondaire",
            "justification": "L'hyperlipidémie secondaire est causée par une autre pathologie ou des médicaments et peut inclure différents types de lipides, mais elle ne se définit pas par une élévation simultanée des cholestérols et des triglycérides."
          },
          {
            "correct": false,
            "proposition": "Dyslipidémie associée au diabète de type 2",
            "justification": "La dyslipidémie associée au diabète de type 2 inclut une élévation des triglycérides et une réduction du cholestérol HDL, mais n'implique pas une augmentation simultanée des cholestérols et des triglycérides."
          }
        ]
      }
    },
    {
      "published": false,
      "id": "AIgenerated_1756050582216_05",
      "current_version_epoch_ms": 1756050582216,
      "rang": "A",
      "topic": {
        "subject": "cardio",
        "item": "dyslip"
      },
      "data": {
        "statement": "Quelles sont les caractéristiques des hyperlipidémies primaires ?",
        "propositions": [
          {
            "correct": true,
            "proposition": "Origine génétique ou familiale",
            "justification": "Les hyperlipidémies primaires sont principalement causées par des facteurs génétiques ou familiaux, comme dans le cas de l'hypercholestérolémie familiale."
          },
          {
            "correct": false,
            "proposition": "Causées par des maladies ou des médicaments",
            "justification": "Ce type de cause est spécifique des hyperlipidémies secondaires, et non des formes primaires."
          },
          {
            "correct": false,
            "proposition": "Associées au diabète de type 2",
            "justification": "Les dyslipidémies associées au diabète de type 2 sont des formes spécifiques qui ne sont pas des hyperlipidémies primaires."
          },
          {
            "correct": false,
            "proposition": "Caractérisées par une élévation des triglycérides uniquement",
            "justification": "Les hyperlipidémies primaires peuvent inclure l'élévation des triglycérides, mais elles peuvent également impliquer des élévations du cholestérol."
          },
          {
            "correct": false,
            "proposition": "Surviennent après une maladie ou un traitement médicamenteux",
            "justification": "Cela décrit les hyperlipidémies secondaires, pas les primaires qui sont génétiques ou familiales."
          }
        ]
      }
    }
  ]
}