{
  "topic": {
    "item": "Sdocclusif",
    "subject": "HGE"
  },
  "metadata": {
    "batch": "IA_aout"
  },
  "question": [
    {
      "published": false,
      "id": "AIgenerated_1756332152753_01",
      "current_version_epoch_ms": 1756332152753,
      "rang": "A",
      "topic": {
        "subject": "HGE",
        "item": "Sdocclusif"
      },
      "data": {
        "statement": "Parmi les étiologies de l'occlusion intestinale chez le nouveau-né, laquelle est caractérisée par des malformations ano-rectales ?",
        "propositions": [
          {
            "correct": true,
            "proposition": "Atrésie intestinale",
            "justification": "L'atrésie intestinale inclut les malformations ano-rectales, qui peuvent entraîner une occlusion intestinale chez le nouveau-né."
          },
          {
            "correct": false,
            "proposition": "Volvulus du grêle sur malrotation",
            "justification": "Le volvulus du grêle sur malrotation est une étiologie de l'occlusion intestinale chez le jeune enfant, pas chez le nouveau-né."
          },
          {
            "correct": false,
            "proposition": "Hernie inguinale étranglée",
            "justification": "La hernie inguinale étranglée est une cause d'occlusion intestinale chez le jeune enfant et non chez le nouveau-né."
          },
          {
            "correct": false,
            "proposition": "Sténose hypertrophique du pylore",
            "justification": "La sténose hypertrophique du pylore se manifeste chez le jeune enfant avec des vomissements non bilieux, mais ne cause pas d'occlusion intestinale chez le nouveau-né."
          },
          {
            "correct": false,
            "proposition": "Iléus méconial",
            "justification": "L'iléus méconial est une manifestation de la mucoviscidose et peut entraîner une occlusion intestinale chez le nouveau-né, mais il ne concerne pas les malformations ano-rectales."
          }
        ]
      }
    },
    {
      "published": false,
      "id": "AIgenerated_1756332152753_02",
      "current_version_epoch_ms": 1756332152753,
      "rang": "A",
      "topic": {
        "subject": "HGE",
        "item": "Sdocclusif"
      },
      "data": {
        "statement": "Quel est le signe clinique principal de la sténose hypertrophique du pylore chez le jeune enfant ?",
        "propositions": [
          {
            "correct": true,
            "proposition": "Vomissements non bilieux",
            "justification": "Les vomissements non bilieux sont caractéristiques de la sténose hypertrophique du pylore chez le jeune enfant."
          },
          {
            "correct": false,
            "proposition": "Selles anormales",
            "justification": "Les selles anormales ne sont pas un signe spécifique de la sténose hypertrophique du pylore, mais peuvent être présentes dans d'autres pathologies."
          },
          {
            "correct": false,
            "proposition": "Fièvre élevée",
            "justification": "La fièvre n'est pas typique de la sténose hypertrophique du pylore, bien qu'elle puisse être présente dans des infections secondaires."
          },
          {
            "correct": false,
            "proposition": "Douleur abdominale intense",
            "justification": "La douleur abdominale intense n'est pas un symptôme prédominant dans la sténose hypertrophique du pylore, contrairement à des vomissements non bilieux."
          },
          {
            "correct": false,
            "proposition": "Distension abdominale",
            "justification": "La distension abdominale n'est pas spécifique de la sténose hypertrophique du pylore et peut être observée dans d'autres pathologies digestives."
          }
        ]
      }
    },
    {
      "published": false,
      "id": "AIgenerated_1756332152753_03",
      "current_version_epoch_ms": 1756332152753,
      "rang": "A",
      "topic": {
        "subject": "HGE",
        "item": "Sdocclusif"
      },
      "data": {
        "statement": "Quel est le mode de révélation de la mucoviscidose qui peut entraîner une occlusion intestinale chez le nouveau-né ?",
        "propositions": [
          {
            "correct": true,
            "proposition": "Iléus méconial",
            "justification": "L'iléus méconial est une forme de constipation grave et une manifestation de la mucoviscidose, pouvant entraîner une occlusion intestinale chez le nouveau-né."
          },
          {
            "correct": false,
            "proposition": "Maladie de Hirschsprung",
            "justification": "La maladie de Hirschsprung est une étiologie d'occlusion intestinale chez le nouveau-né, mais elle n'est pas liée à la mucoviscidose."
          },
          {
            "correct": false,
            "proposition": "Volvulus du grêle sur malrotation",
            "justification": "Le volvulus du grêle sur malrotation est une étiologie de l'occlusion intestinale, mais il n'est pas lié à la mucoviscidose."
          },
          {
            "correct": false,
            "proposition": "Sténose hypertrophique du pylore",
            "justification": "La sténose hypertrophique du pylore se manifeste par des vomissements non bilieux chez le jeune enfant, mais elle n'entraîne pas une occlusion intestinale."
          },
          {
            "correct": false,
            "proposition": "Hernie inguinale étranglée",
            "justification": "La hernie inguinale étranglée est une cause d'occlusion intestinale chez le jeune enfant, mais elle n'est pas en lien avec la mucoviscidose."
          }
        ]
      }
    },
    {
      "published": false,
      "id": "AIgenerated_1756332152753_04",
      "current_version_epoch_ms": 1756332152753,
      "rang": "A",
      "topic": {
        "subject": "HGE",
        "item": "Sdocclusif"
      },
      "data": {
        "statement": "Quel est le signe clinique principal de l'invagination intestinale aiguë chez le jeune enfant ?",
        "propositions": [
          {
            "correct": true,
            "proposition": "Douleur abdominale paroxystique",
            "justification": "L'invagination intestinale aiguë se manifeste souvent par des douleurs abdominales paroxystiques, qui sont caractéristiques de cette pathologie."
          },
          {
            "correct": false,
            "proposition": "Vomissements bilieux",
            "justification": "Les vomissements bilieux ne sont pas spécifiques de l'invagination intestinale aiguë, mais peuvent survenir dans d'autres pathologies."
          },
          {
            "correct": false,
            "proposition": "Distension abdominale massive",
            "justification": "La distension abdominale massive n'est pas un signe majeur de l'invagination intestinale aiguë, qui se caractérise par des douleurs paroxystiques."
          },
          {
            "correct": false,
            "proposition": "Selles noires",
            "justification": "Les selles noires ne sont pas un signe spécifique de l'invagination intestinale aiguë, mais peuvent être dues à un saignement digestif."
          },
          {
            "correct": false,
            "proposition": "Fièvre élevée",
            "justification": "La fièvre n'est pas un signe spécifique de l'invagination intestinale aiguë, bien qu'elle puisse apparaître en cas de complications comme la péritonite."
          }
        ]
      }
    },
    {
      "published": false,
      "id": "AIgenerated_1756332152753_05",
      "current_version_epoch_ms": 1756332152753,
      "rang": "A",
      "topic": {
        "subject": "HGE",
        "item": "Sdocclusif"
      },
      "data": {
        "statement": "Quelle est l'étiologie principale de l'occlusion intestinale chez l'enfant plus âgé ?",
        "propositions": [
          {
            "correct": true,
            "proposition": "Occlusion sur bride",
            "justification": "L'occlusion sur bride est l'étiologie la plus fréquente de l'occlusion intestinale chez l'enfant plus âgé, souvent liée à une intervention chirurgicale antérieure."
          },
          {
            "correct": false,
            "proposition": "Invagination intestinale aiguë",
            "justification": "L'invagination intestinale aiguë est plus fréquente chez les jeunes enfants, et moins courante chez les enfants plus âgés."
          },
          {
            "correct": false,
            "proposition": "Hernie inguinale étranglée",
            "justification": "Bien que la hernie inguinale étranglée soit une cause d'occlusion intestinale, elle est plus fréquente chez les jeunes enfants."
          },
          {
            "correct": false,
            "proposition": "Volvulus du grêle sur malrotation",
            "justification": "Le volvulus du grêle sur malrotation est une cause d'occlusion intestinale pouvant survenir à tout âge, mais il est plus fréquent chez le jeune enfant."
          },
          {
            "correct": false,
            "proposition": "Péritonite",
            "justification": "La péritonite peut être une complication de l'occlusion intestinale, mais elle n'est pas une étiologie primaire de l'occlusion chez l'enfant plus âgé."
          }
        ]
      }
    }
  ]
}