{
  "topic": {
    "item": "FdRCV",
    "subject": "cardio"
  },
  "metadata": {
    "batch": "IA_aout"
  },
  "question": [
    {
      "published": false,
      "id": "AIgenerated_1756049225203_01",
      "current_version_epoch_ms": 1756049225203,
      "rang": "A",
      "topic": {
        "subject": "cardio",
        "item": "FdRCV"
      },
      "data": {
        "statement": "Quel est l'effet bénéfique de l'activité physique sur la pression artérielle ?",
        "propositions": [
          {
            "correct": true,
            "proposition": "L'activité physique permet de diminuer la pression artérielle.",
            "justification": "L'activité physique a un effet direct sur la baisse de la pression artérielle, ce qui est l'un des principaux bénéfices cardiovasculaires."
          },
          {
            "correct": false,
            "proposition": "L'activité physique n'a aucun effet sur la pression artérielle.",
            "justification": "Cela est incorrect, car l'activité physique a démontré une réduction significative de la pression artérielle."
          },
          {
            "correct": false,
            "proposition": "L'activité physique augmente la pression artérielle de manière significative.",
            "justification": "Cette proposition est incorrecte, l'activité physique a un effet bénéfique en réduisant la pression artérielle."
          },
          {
            "correct": false,
            "proposition": "L'activité physique augmente uniquement la pression artérielle pendant l'effort.",
            "justification": "Il est vrai que la pression artérielle augmente durant l'effort, mais les effets à long terme de l'activité physique sont bénéfiques et réduisent la pression artérielle."
          },
          {
            "correct": false,
            "proposition": "L'activité physique diminue la pression artérielle uniquement chez les personnes âgées.",
            "justification": "Cela est incorrect, car l'effet bénéfique sur la pression artérielle est observé dans tous les groupes d'âge, y compris les jeunes adultes."
          }
        ]
      }
    },
    {
      "published": false,
      "id": "AIgenerated_1756049225203_02",
      "current_version_epoch_ms": 1756049225203,
      "rang": "A",
      "topic": {
        "subject": "cardio",
        "item": "FdRCV"
      },
      "data": {
        "statement": "Quel effet l'activité physique a-t-elle sur les lipides sanguins ?",
        "propositions": [
          {
            "correct": true,
            "proposition": "L'activité physique diminue le LDL-c et les triglycérides tout en augmentant le HDL-c.",
            "justification": "L'activité physique a un effet direct sur l'amélioration du profil lipidique, avec une baisse du LDL-c et des triglycérides, et une augmentation du HDL-c."
          },
          {
            "correct": false,
            "proposition": "L'activité physique augmente le LDL-c et le HDL-c.",
            "justification": "Cette proposition est incorrecte, car l'activité physique réduit le LDL-c et augmente le HDL-c."
          },
          {
            "correct": false,
            "proposition": "L'activité physique n'a aucun effet sur les lipides sanguins.",
            "justification": "Cela est incorrect, car l'activité physique a des effets significatifs sur la réduction des lipides sanguins, en particulier le LDL-c et les triglycérides."
          },
          {
            "correct": false,
            "proposition": "L'activité physique diminue uniquement les triglycérides.",
            "justification": "Cela est incorrect, car l'activité physique a un impact à la fois sur le LDL-c, les triglycérides et le HDL-c."
          },
          {
            "correct": false,
            "proposition": "L'activité physique diminue uniquement le HDL-c.",
            "justification": "Cette proposition est incorrecte, car l'activité physique augmente le HDL-c tout en réduisant le LDL-c et les triglycérides."
          }
        ]
      }
    },
    {
      "published": false,
      "id": "AIgenerated_1756049225203_03",
      "current_version_epoch_ms": 1756049225203,
      "rang": "A",
      "topic": {
        "subject": "cardio",
        "item": "FdRCV"
      },
      "data": {
        "statement": "Quel est l'impact de l'activité physique sur la glycémie et l'insulinorésistance ?",
        "propositions": [
          {
            "correct": true,
            "proposition": "L'activité physique améliore le contrôle glycémique en diminuant l'insulinorésistance.",
            "justification": "L'activité physique est bénéfique pour améliorer la sensibilité à l'insuline, ce qui permet un meilleur contrôle glycémique."
          },
          {
            "correct": false,
            "proposition": "L'activité physique augmente l'insulinorésistance.",
            "justification": "Cette proposition est incorrecte, car l'activité physique réduit l'insulinorésistance et améliore le contrôle glycémique."
          },
          {
            "correct": false,
            "proposition": "L'activité physique n'a aucun effet sur l'insulinorésistance.",
            "justification": "C'est incorrect, car des études ont montré que l'activité physique réduit l'insulinorésistance."
          },
          {
            "correct": false,
            "proposition": "L'activité physique diminue la production d'insuline mais n'affecte pas la glycémie.",
            "justification": "Cela est incorrect, car l'activité physique améliore à la fois la production d'insuline et le contrôle glycémique."
          },
          {
            "correct": false,
            "proposition": "L'activité physique réduit uniquement la glycémie après un repas.",
            "justification": "Cette proposition est incorrecte, car l'activité physique a des effets à long terme sur la réduction de la glycémie et de l'insulinorésistance."
          }
        ]
      }
    },
    {
      "published": false,
      "id": "AIgenerated_1756049225203_04",
      "current_version_epoch_ms": 1756049225203,
      "rang": "A",
      "topic": {
        "subject": "cardio",
        "item": "FdRCV"
      },
      "data": {
        "statement": "Quel est l'impact de l'activité physique sur la mortalité cardiovasculaire ?",
        "propositions": [
          {
            "correct": true,
            "proposition": "L'activité physique régulière peut réduire la mortalité cardiovasculaire de 30%.",
            "justification": "L'activité physique régulière a montré des effets significatifs sur la réduction de la mortalité cardiovasculaire, avec une diminution de 30% observée."
          },
          {
            "correct": false,
            "proposition": "L'activité physique n'a aucun effet sur la mortalité cardiovasculaire.",
            "justification": "Cela est incorrect, car l'activité physique réduit de manière significative la mortalité cardiovasculaire."
          },
          {
            "correct": false,
            "proposition": "L'activité physique augmente la mortalité cardiovasculaire.",
            "justification": "Cette proposition est incorrecte, car l'activité physique est bénéfique et réduit la mortalité cardiovasculaire."
          },
          {
            "correct": false,
            "proposition": "L'activité physique ne réduit la mortalité cardiovasculaire que chez les personnes âgées.",
            "justification": "Cela est incorrect, l'impact bénéfique de l'activité physique sur la mortalité cardiovasculaire est observé chez toutes les tranches d'âge."
          },
          {
            "correct": false,
            "proposition": "L'activité physique ne réduit que les maladies cardiaques mais pas la mortalité cardiovasculaire.",
            "justification": "C'est incorrect, car l'activité physique réduit à la fois les maladies cardiaques et la mortalité cardiovasculaire."
          }
        ]
      }
    },
    {
      "published": false,
      "id": "AIgenerated_1756049225203_05",
      "current_version_epoch_ms": 1756049225203,
      "rang": "A",
      "topic": {
        "subject": "cardio",
        "item": "FdRCV"
      },
      "data": {
        "statement": "Quel est l'impact de l'activité physique sur le poids corporel ?",
        "propositions": [
          {
            "correct": true,
            "proposition": "L'activité physique contribue à la perte de poids.",
            "justification": "L'activité physique régulière permet une dépense énergétique qui aide à réduire le poids corporel."
          },
          {
            "correct": false,
            "proposition": "L'activité physique n'a pas d'effet sur le poids corporel.",
            "justification": "Cela est incorrect, l'activité physique joue un rôle clé dans la gestion du poids."
          },
          {
            "correct": false,
            "proposition": "L'activité physique augmente le poids corporel indépendamment de l'alimentation.",
            "justification": "Cela est incorrect, l'activité physique a un effet bénéfique sur la perte de poids et peut être combinée à un régime alimentaire pour de meilleurs résultats."
          },
          {
            "correct": false,
            "proposition": "L'activité physique diminue uniquement la graisse abdominale.",
            "justification": "Cela est incorrect, car l'activité physique affecte l'ensemble du corps et aide à réduire la graisse corporelle dans son ensemble."
          },
          {
            "correct": false,
            "proposition": "L'activité physique n'est utile que pour les personnes en surpoids.",
            "justification": "Cette proposition est incorrecte, car l'activité physique bénéficie à toutes les personnes, quel que soit leur poids."
          }
        ]
      }
    }
  ]
}