[
    {
        "identifiant": "OIC-113-01-A",
        "rang": "A",
        "intitule": "Connaître la définition d'un hémangiome et son histoire naturelle",
        "content": "\nConnaître la définition d'un hémangiome et son histoire naturelle OIC-113-01-A\n\n\n\n\n\n séquelle d’un hémangiome superficiel à l’âge de 5 ans\n1-     Définition\n•               Prolifération de cellules endothéliales post natale de cause inconnue.\n•               Tumeurs vasculaire fréquente (10 % des nourrissons). Plus fréquentes chez les filles, les prématurés et les nouveau-nés de faible poids de naissance.\n2-     Histoire naturelle: \n•               Absent à la naissance (ou précédé par une macule télangiectasique avec halo périphérique de vasoconstriction ) = notion d’intervalle libre\n•               Phase de croissance à partir de l’âge de quelques jours à quelques semaines et pendant 5 à 6 mois\n•               Phase d'involution spontanée (pendant 2 à 10 ans) débutant par un blanchiment en surface\n•               A la fin de phase d’involution  :\n•    50% : régression totale sans séquelles\n\n•            50% : séquelle de type télangiectasies ou nodule fibro-adipeux (Figure 113.1 ) nécessitant parfois un geste thérapeutique. Connaître la définition d'un hémangiome et son histoire naturelle OIC-113-01-Aséquelle d’un hémangiome superficiel à l’âge de 5 ans1-     Définition•               Prolifération de cellules endothéliales post natale de cause inconnue.•               Tumeurs vasculaire fréquente (10 % des nourrissons). Plus fréquentes chez les filles, les prématurés et les nouveau-nés de faible poids de naissance.2-Histoire naturelle:•               Absent à la naissance (ou précédé par une macule télangiectasique avec halo périphérique de vasoconstriction ) = notion d’intervalle libre•               Phase de croissance à partir de l’âge de quelques jours à quelques semaines et pendant 5 à 6 mois•               Phase d'involution spontanée (pendant 2 à 10 ans) débutant par un blanchiment en surface•               A la fin de phase d’involution  :•    50% : régression totale sans séquelles•            50% : séquelle de type télangiectasies ou nodule fibro-adipeux (Figure 113.1 ) nécessitant parfois un geste thérapeutique."
    },
    {
        "identifiant": "OIC-113-02-A",
        "rang": "A",
        "intitule": "Connaître les signes cliniques d'un hémangiome",
        "content": "\nConnaître les signes cliniques d'un hémangiome OIC-113-02-A\n\n\n\n\n\n Fig 113.2: hémangiome superficiel\n Figure 113.3 : hémangiome mixte\n1-     Diagnostic clinique ( biopsie et imagerie généralement inutiles).\n•               Tuméfaction de consistance élastique (non dure) sans frémissement à la palpation ni souffle à l’auscultation.\n•               Taille, nombre et siège variables. \nTrois types cliniques d’hémangiome :\n•            Hémangiome superficiel (= nodule ou une plaque rouge vif (figure 113.2), en relief, à surface tendue ou mamelonnée, sans vidange ni disparition complète à la pression.\n•            Hémangiome profond (ou sous-cutané) = tuméfaction bleutée ou de la couleur de la peau normale (imagerie parfois nécessaire : l'échographie-Doppler montre une tumeur richement vascularisée à flux rapide).\n\n•            Hémangiome mixte associe les composantes superficielle et profonde (figure 113.3). Connaître les signes cliniques d'un hémangiome OIC-113-02-AFig 113.2: hémangiome superficielFigure 113.3 : hémangiome mixte1-     Diagnostic clinique( biopsie et imagerie généralement inutiles).•               Tuméfaction de consistance élastique (non dure) sans frémissement à la palpation ni souffle à l’auscultation.•               Taille, nombre et siège variables.Trois types cliniques d’hémangiome:•Hémangiome superficiel(= nodule ou une plaque rouge vif (figure 113.2), en relief, à surface tendue ou mamelonnée, sans vidange ni disparition complète à la pression.•Hémangiome profond(ou sous-cutané) = tuméfaction bleutée ou de la couleur de la peau normale (imagerie parfois nécessaire : l'échographie-Doppler montre une tumeur richement vascularisée à flux rapide).•Hémangiome mixteassocie les composantes superficielle et profonde (figure 113.3)."
    },
    {
        "identifiant": "OIC-113-04-A",
        "rang": "A",
        "intitule": "Connaître les localisations à risque et les complications des hémangiomes",
        "content": "\nSommaire\n\n1 Connaître les localisations à risque et les complications des hémangiomes OIC-113-04-A\n\n1.1 1-     Ulcération\n1.2 2-     Hémangiomes orbito-palpébraux\n1.3 3-     Hémangiomes de la pointe du nez, hémangiomes volumineux du visage (Figure 113.5) et de la région mammaire chez la fille\n1.4 4-     Hémangiomes sous-glottiques\n1.5 5-     Hémangiomatose miliaire\n1.6 6-     Hémangiomes segmentaires associés à des malformations\n\n\n\n\nConnaître les localisations à risque et les complications des hémangiomes OIC-113-04-A\n\n\n\n\n\n Figure 113.4 : hémangiome ulcéré\n Figure 113.5 : hémangiome volumineux du visage avec risque de séquelle esthétique\n Figure 113.6 : hémangiome « en barbe » avec localisation sous glottique et dyspnée\n·      10 % des hémangiomes infantiles se compliquent (cf 6 situations ci-dessous) et nécessitent\no  Un avis et un suivi spécialisé\no  un traitement précoce (le traitement de première intention dans ces cas est le propranolol per os)\n\n\n1-     Ulcération\nL’ulcération fait suite à une nécrose partielle de l’hémangiome (Figure 113.4). Les localisations à risque sont: le siège (fesses, vulve), les lèvres, les plis (cou).\nConséquences possibles :\n•               douleurs, majorées par les mictions en cas d'atteinte du siège et gênant l’alimentation en cas de localisation péri orale;\n•               saignements\n•               cicatrice séquellaire\nFigure 113.4 : hémangiome ulcéré\n\n2-     Hémangiomes orbito-palpébraux\nRisque d'amblyopie fonctionnelle par occlusion du champ visuel et/ou déformation de la cornée (compression)\n\n3-     Hémangiomes de la pointe du nez, hémangiomes volumineux du visage (Figure 113.5) et de la région mammaire chez la fille\nRisque de cicatrice séquellaire\nFigure 113.5 : hémangiome volumineux du visage avec risque de séquelle esthétique\n\n4-     Hémangiomes sous-glottiques\n•               Risque de détresse respiratoire par compression laryngée\n•               Peuvent être isolés ou associés à un hémangiome cutané « en barbe » (localisé symétriquement aux régions mandibulaires, mentonnière, cervicales et lèvre inférieure) => exploration endoscopique ORL nécessaire si hémangiome situé dans ces régions et avis spécialisé (Figure 113.6)\nFigure 113.6 : hémangiome « en barbe » avec localisation sous glottique et dyspnée\n\n\n5-     Hémangiomatose miliaire\n•               Multiples petits hémangiomes disséminés de quelques millimètres à 1 cm de diamètre\n•               Peuvent être associés à des hémangiomes hépatiques parfois volumineux\n•               Demander une échographie abdominale et avis spécialisé\n\n6-     Hémangiomes segmentaires associés à des malformations\nDe rares hémangiomes en plaques (dits segmentaires) peuvent s'accompagner de malformations qui varient selon leur localisation :\n•               Visage et extrémité céphalique : malformations du cervelet, cardiaques, des gros vaisseaux, oculaires, sternales (syndrome PHACES) ;\n•               Région périnéale et lombosacrée : malformations anorectales et génito-urinaires, dysraphie spinale (syndrome PELVIS ou SACRAL).\n\nUn hémangiome segmentaire de ces régions justifie une IRM et une prise en charge spécialisée multidisciplinaire. Sommaire1Connaître les localisations à risque et les complications des hémangiomes OIC-113-04-A1.11-     Ulcération1.22-     Hémangiomes orbito-palpébraux1.33-     Hémangiomes de la pointe du nez, hémangiomes volumineux du visage (Figure 113.5) et de la région mammaire chez la fille1.44-     Hémangiomes sous-glottiques1.55-     Hémangiomatose miliaire1.66-     Hémangiomes segmentaires associés à des malformationsConnaître les localisations à risque et les complications des hémangiomes OIC-113-04-AFigure 113.4 : hémangiome ulcéréFigure 113.5 : hémangiome volumineux du visage avec risque de séquelle esthétiqueFigure 113.6 : hémangiome « en barbe » avec localisation sous glottique et dyspnée·      10 % des hémangiomes infantiles se compliquent (cf 6 situations ci-dessous) et nécessitento  Un avis et un suivi spécialiséo  un traitement précoce (le traitement de première intention dans ces cas est lepropranolol per os)1-     UlcérationL’ulcération fait suite à une nécrose partielle de l’hémangiome (Figure 113.4). Les localisations à risque sont: le siège (fesses, vulve), les lèvres, les plis (cou).Conséquences possibles :•               douleurs, majorées par les mictions en cas d'atteinte du siège et gênant l’alimentation en cas de localisation péri orale;•               saignements•               cicatrice séquellaireFigure 113.4 : hémangiome ulcéré2-     Hémangiomes orbito-palpébrauxRisque d'amblyopie fonctionnelle par occlusion du champ visuel et/ou déformation de la cornée (compression)3-     Hémangiomes de la pointe du nez, hémangiomes volumineux du visage (Figure 113.5) et de la région mammaire chez la filleRisque de cicatrice séquellaireFigure 113.5 : hémangiome volumineux du visage avec risque de séquelle esthétique4-     Hémangiomes sous-glottiques•               Risque de détresse respiratoire par compression laryngée•               Peuvent être isolés ou associés à un hémangiome cutané« en barbe »(localisé symétriquement aux régions mandibulaires, mentonnière, cervicales et lèvre inférieure) => exploration endoscopique ORL nécessaire si hémangiome situé dans ces régions et avis spécialisé (Figure 113.6)Figure 113.6 : hémangiome « en barbe » avec localisation sous glottique et dyspnée5-     Hémangiomatose miliaire•               Multiples petits hémangiomes disséminés de quelques millimètres à 1 cm de diamètre•               Peuvent être associés à des hémangiomes hépatiques parfois volumineux•               Demander une échographie abdominale et avis spécialisé6-     Hémangiomes segmentaires associés à des malformationsDe rares hémangiomes en plaques (dits segmentaires) peuvent s'accompagner de malformations qui varient selon leur localisation :•               Visage et extrémité céphalique : malformations du cervelet, cardiaques, des gros vaisseaux, oculaires, sternales (syndrome PHACES) ;•               Région périnéale et lombosacrée : malformations anorectales et génito-urinaires, dysraphie spinale (syndrome PELVIS ou SACRAL).Un hémangiome segmentaire de ces régions justifie une IRM et une prise en charge spécialisée multidisciplinaire."
    },
    {
        "identifiant": "OIC-113-03-B",
        "rang": "B",
        "intitule": "Connaître les principaux diagnostics différentiels des hémangiomes",
        "content": "\nSommaire\n\n1 Connaître les localisations à risque et les complications des hémangiomes OIC-113-04-A\n\n1.1 1-     Ulcération\n1.2 2-     Hémangiomes orbito-palpébraux\n1.3 3-     Hémangiomes de la pointe du nez, hémangiomes volumineux du visage (Figure 113.5) et de la région mammaire chez la fille\n1.4 4-     Hémangiomes sous-glottiques\n1.5 5-     Hémangiomatose miliaire\n1.6 6-     Hémangiomes segmentaires associés à des malformations\n\n\n\n\nConnaître les principaux diagnostics différentiels des hémangiomes OIC-113-03-B\n\n\n\n\n\n\n\n\n\n\n\nHémangiome infantile\n\nMalformation vasculaire\n\n\nA la naissance\n\nAbsent\n\nPrésent\n\n\nEvolution\n\nCroissance en volume puis régression au cours des\n5 premières années de vie\n\n\nStabilité ou aggravation\nPersistance\n\n\n\nPrincipaux types\n\nHémangiomes superficiels, profonds et mixtes\n\nMalformations capillaires (ou angiomes plans)\nMalformations veineuses\nMalformations lymphatiques\nMalformations artério-veineuses\nMalformations mixtes\n\n\n\n\n1-      Tumeurs malignes du nourrisson\nUne tumeur maligne vascularisée (rhabdomyosarcome, fibrosarcome infantile…) est à évoquer devant une tumeur congénitale, unique, dure, évolutive =>biopsie au moindre doute.\n\n2-      Malformations vasculaires (cf tableau 1)\n·      Un hémangiome superficiel au stade initial peut simuler une malformation vasculaire (angiome plan).\n·      Certaines malformations veineuses ou lymphatiques peuvent simuler un hémangiome profond sous-cutané (l'échographie-Doppler met en évidence un flux rapide dans les hémangiomes et un flux lent dans les malformations veineuses ou lymphatiques).\n\n3-     Hémangiomes congénitaux\n·      Entité différente des hémangiomes infantiles.\n·      Présents à la naissance, parfois dépistés par l'échographie anténatale.\n·      évolution variable : régression rapide ou persistance.\n·      Propranolol inefficace\n\n\n4-     Syndrome de Kasabach-Merritt\n·      Phénomène de coagulation intravasculaire tumorale associé à une thrombopénie.\n·      Ne complique pas sur les hémangiomes infantiles mais des tumeurs vasculaires congénitales rares.\n·      Apparition rapide d’une tuméfaction volumineuse, ecchymotique et inflammatoire.\n\n·      Prise en charge hospitalière spécialisée. Sommaire1Connaître les localisations à risque et les complications des hémangiomes OIC-113-04-A1.11-     Ulcération1.22-     Hémangiomes orbito-palpébraux1.33-     Hémangiomes de la pointe du nez, hémangiomes volumineux du visage (Figure 113.5) et de la région mammaire chez la fille1.44-     Hémangiomes sous-glottiques1.55-     Hémangiomatose miliaire1.66-     Hémangiomes segmentaires associés à des malformationsConnaître les principaux diagnostics différentiels des hémangiomes OIC-113-03-BHémangiome infantileMalformation vasculaireA la naissanceAbsentPrésentEvolutionCroissance en volume puis régression au cours des5 premières années de vieStabilité ou aggravationPersistancePrincipaux typesHémangiomes superficiels, profonds et mixtesMalformations capillaires (ou angiomes plans)Malformations veineusesMalformations lymphatiquesMalformations artério-veineusesMalformations mixtes1-      Tumeurs malignes du nourrissonUne tumeur maligne vascularisée (rhabdomyosarcome, fibrosarcome infantile…) est à évoquer devant une tumeur congénitale, unique, dure, évolutive =>biopsie au moindre doute.2-Malformations vasculaires (cf tableau 1)·      Un hémangiome superficiel au stade initial peut simuler une malformation vasculaire (angiome plan).·      Certaines malformations veineuses ou lymphatiques peuvent simuler un hémangiome profond sous-cutané (l'échographie-Doppler met en évidence un flux rapide dans les hémangiomes et un flux lent dans les malformations veineuses ou lymphatiques).3-     Hémangiomes congénitaux·      Entité différente des hémangiomes infantiles.·      Présents à la naissance, parfois dépistés par l'échographie anténatale.·      évolution variable : régression rapide ou persistance.·      Propranolol inefficace4-     Syndrome de Kasabach-Merritt·      Phénomène de coagulation intravasculaire tumorale associé à une thrombopénie.·      Ne complique pas sur les hémangiomes infantiles mais des tumeurs vasculaires congénitales rares.·      Apparition rapide d’une tuméfaction volumineuse, ecchymotique et inflammatoire.·      Prise en charge hospitalière spécialisée."
    },
    {
        "identifiant": "OIC-113-05-B",
        "rang": "B",
        "intitule": "Connaître les modalités du diagnostic d'une d'un angiome plan",
        "content": "\nConnaître les modalités du diagnostic d'une d'un angiome plan OIC-113-05-B\n\n\n\n\n\n Figure 113.7: syndrome de Sturge Weber\n Figure 113.8 Angiome flammeus régressif\n\n\n1-     Diagnostic positif\n·      Le diagnostic est clinique\n·      Macules rouges congénitales de même température que la peau normale s’effaçant à la vitropression\n·      Toujours présentes à la naissance et évoluent peu.\n·      Localisations variées\n·      Habituellement isolés (non associés à d’autres malformations) sauf atteinte de la partie supérieure de l’hémiface => doit faire rechercher des malformations oculaires et cérébrales associées (syndrome de Sturge Weber). Figure 113.7\nFigure 113.7\n·      Augmentent en surface proportionnellement à la croissance de l'enfant\n·      Persistent toute la vie\n.\n\n2-     Diagnostic différentiel\n·      Taches angiomateuses physiologiques du nouveau-né : très fréquentes chez le nouveau-né, plus pâles (rose), localisées en interorbitaire (angiome flammeus) (Figure 113.8) le front, les paupières supérieures ou l'occiput, évoluant vers le pâlissement (sauf sur la nuque et l'occiput) ;\n\n·      Hémangiome infantile au stade précoce (cf supra) ; Connaître les modalités du diagnostic d'une d'un angiome plan OIC-113-05-BFigure 113.7: syndrome de Sturge WeberFigure 113.8 Angiome flammeus régressif1-     Diagnostic positif·      Le diagnostic est clinique·      Macules rouges congénitales de même température que la peau normale s’effaçant à la vitropression·      Toujours présentes à la naissance et évoluent peu.·      Localisations variées·      Habituellement isolés (non associés à d’autres malformations) sauf atteinte de la partie supérieure de l’hémiface => doit faire rechercher des malformations oculaires et cérébrales associées (syndrome de Sturge Weber). Figure 113.7Figure 113.7·      Augmentent en surface proportionnellement à la croissance de l'enfant·      Persistent toute la vie.2-     Diagnostic différentiel·Taches angiomateuses physiologiques du nouveau-né: très fréquentes chez le nouveau-né, plus pâles (rose), localisées en interorbitaire (angiome flammeus) (Figure 113.8) le front, les paupières supérieures ou l'occiput, évoluant vers le pâlissement (sauf sur la nuque et l'occiput) ;·Hémangiome infantile au stade précoce(cf supra) ;"
    },
    {
        "identifiant": "OIC-113-06-B",
        "rang": "B",
        "intitule": "Connaître les complications d'une malformation veineuse",
        "content": "\nConnaître les complications d'une malformation veineuse OIC-113-06-B\n\n\n\n Figure 113.9 Malformation veineuse de la main\n1-     Diagnostic\nLes malformations veineuses se manifestent par une ou des tuméfactions bleutées sous-cutanées ou veines dilatées superficielles semblables à des varices (Figure 113.9)\n•      molles, dépressibles ;\n•      se vidant à la pression ou à la surélévation du membre ; gonflant en position déclive, lors des efforts ou des cris (visage) ;\n•      sans augmentation de la chaleur locale, ni battement, ni souffle ;\n•      de volume et d'étendue variables.\n•      Extension profonde possible (loges musculaires des membres).\n•      peuvent se révéler tardivement à l'occasion d'une poussée évolutive survenant après un traumatisme, une infection, à la puberté, lors d'une grossesse.\n•      L'écho-Doppler est indiqué = met en évidence des lacs veineux et l'absence de flux spontané.\n•      Avis spécialisé indispensable\n\n•     2-     Évolution, complications\n•      Aggravation lente au cours de la vie.\n•      Episodes aigus de (micro) thrombose au sein de la malformation fréquents (nodule douloureux évoluant vers la calcification : phlébolithes palpables et visibles à la radiographie).\n\n Connaître les complications d'une malformation veineuse OIC-113-06-BFigure 113.9 Malformation veineuse de la main1-     DiagnosticLesmalformations veineusesse manifestent par une ou des tuméfactions bleutées sous-cutanées ou veines dilatées superficielles semblables à des varices (Figure 113.9)•      molles, dépressibles ;•      se vidant à la pression ou à la surélévation du membre ; gonflant en position déclive, lors des efforts ou des cris (visage) ;•      sans augmentation de la chaleur locale, ni battement, ni souffle ;•      de volume et d'étendue variables.•      Extension profonde possible (loges musculaires des membres).•      peuvent se révéler tardivement à l'occasion d'une poussée évolutive survenant après un traumatisme, une infection, à la puberté, lors d'une grossesse.•      L'écho-Doppler est indiqué = met en évidence des lacs veineux et l'absence de flux spontané.•      Avis spécialisé indispensable•     2-     Évolution, complications•      Aggravation lente au cours de la vie.•      Episodes aigus de (micro) thrombose au sein de la malformation fréquents (nodule douloureux évoluant vers la calcification : phlébolithes palpables et visibles à la radiographie)."
    },
    {
        "identifiant": "OIC-113-07-B",
        "rang": "B",
        "intitule": "Connaître les complications d'une malformation artério-veineuse",
        "content": "\nConnaître les complications d'une malformation artério-veineuse OIC-113-07-B\n\n\n\n1-     Diagnostic positif\n•      Les malformations artério-veineuses se manifestent par une ou des macules rouges simulant un angiome plan mais chaudes, extensives et battantes, évoluant vers une tuméfaction ou une déformation localisée.\n•      Le diagnostic se fait sur :\n•      la palpation : frémissement (thrill) ;\n•      l'auscultation : souffle ;\n•       l'échographie-Doppler : flux rapide.\n•       la localisation : oreilles, cuir chevelu et extrémités des membres sont les plus fréquemment touchés.\n•      IRM indiquée.\n•      Avis spécialisé indispensable\n\n2-     Évolution et complications\n•      Par poussées spontanées ou déclenchées par un traumatisme ou une tentative de geste thérapeutique, la puberté ou lors d'une grossesse.\n\n•      Risque d'hémorragie, de nécrose ischémique, d'invasion locorégionale, de récidives après traitement Connaître les complications d'une malformation artério-veineuse OIC-113-07-B1-     Diagnostic positif•      Lesmalformations artério-veineusesse manifestent par une ou des macules rouges simulant un angiome plan mais chaudes, extensives et battantes, évoluant vers une tuméfaction ou une déformation localisée.•      Le diagnostic se fait sur :•      la palpation : frémissement (thrill) ;•      l'auscultation : souffle ;•       l'échographie-Doppler : flux rapide.•       la localisation : oreilles, cuir chevelu et extrémités des membres sont les plus fréquemment touchés.•      IRM indiquée.•      Avis spécialisé indispensable2-Évolution et complications•      Par poussées spontanées ou déclenchées par un traumatisme ou une tentative de geste thérapeutique, la puberté ou lors d'une grossesse.•      Risque d'hémorragie, de nécrose ischémique, d'invasion locorégionale, de récidives après traitement"
    }
]